setup.py
truthy/__init__.py
truthy/__main__.py
truthy/expression.py
truthy/parse.py
truthy.egg-info/PKG-INFO
truthy.egg-info/SOURCES.txt
truthy.egg-info/dependency_links.txt
truthy.egg-info/not-zip-safe
truthy.egg-info/requires.txt
truthy.egg-info/top_level.txt