Metadata-Version: 1.0
Name: truthy
Version: 0.3
Summary: Small utility for parsing logic expressions and generating truth tables.
Home-page: https://github.com/mtomwing/truthy
Author: Michael Tom-Wing
Author-email: mtomwing@gmail.com
License: GPLv2
Platform: UNKNOWN
